djblets/__init__.py
djblets/dependencies.py
djblets/deprecation.py
djblets/package.json
djblets/py.typed
djblets/settings.py
djblets/staticbundles.py
djblets/auth/__init__.py
djblets/auth/apps.py
djblets/auth/forms.py
djblets/auth/ratelimit.py
djblets/auth/signals.py
djblets/auth/urls.py
djblets/auth/util.py
djblets/auth/views.py
djblets/auth/templates/accounts/register.html
djblets/auth/tests/__init__.py
djblets/auth/tests/test_ratelimit.py
djblets/auth/tests/test_registration_form.py
djblets/auth/tests/test_util.py
djblets/auth/tests/test_views.py
djblets/avatars/__init__.py
djblets/avatars/apps.py
djblets/avatars/errors.py
djblets/avatars/forms.py
djblets/avatars/registry.py
djblets/avatars/settings.py
djblets/avatars/tests.py
djblets/avatars/services/__init__.py
djblets/avatars/services/base.py
djblets/avatars/services/fallback.py
djblets/avatars/services/file_upload.py
djblets/avatars/services/gravatar.py
djblets/avatars/services/url.py
djblets/avatars/templates/avatars/avatar.html
djblets/avatars/templates/avatars/fallback.html
djblets/avatars/templates/avatars/service_form.html
djblets/avatars/templates/avatars/settings_form.html
djblets/avatars/templates/avatars/services/file_upload_form.html
djblets/cache/__init__.py
djblets/cache/apps.py
djblets/cache/backend.py
djblets/cache/backend_compat.py
djblets/cache/context_processors.py
djblets/cache/errors.py
djblets/cache/forwarding_backend.py
djblets/cache/serials.py
djblets/cache/synchronizer.py
djblets/cache/tests/__init__.py
djblets/cache/tests/test_backend.py
djblets/cache/tests/test_synchronizer.py
djblets/conditions/__init__.py
djblets/conditions/choices.py
djblets/conditions/conditions.py
djblets/conditions/errors.py
djblets/conditions/operators.py
djblets/conditions/values.py
djblets/conditions/tests/__init__.py
djblets/conditions/tests/test_choices.py
djblets/conditions/tests/test_conditions.py
djblets/conditions/tests/test_operators.py
djblets/conditions/tests/test_values.py
djblets-5.2.1.dist-info/licenses/AUTHORS
djblets-5.2.1.dist-info/METADATA
djblets-5.2.1.dist-info/WHEEL
djblets-5.2.1.dist-info/top_level.txt
djblets-5.2.1.dist-info/RECORD
