Metadata-Version: 2.4
Name: Djblets
Version: 5.2.1
Summary: A collection of useful classes and functions for developing large-scale Django-based web applications.
Author-email: "Beanbag, Inc." <questions@beanbaginc.com>
License: MIT
Project-URL: Homepage, https://github.com/djblets/djblets
Project-URL: Documentation, https://github.com/djblets/djblets
Project-URL: Repository, https://github.com/djblets/djblets
Project-URL: Support, https://www.reviewboard.org/support/
Classifier: Development Status :: 5 - Production/Stable
Classifier: Environment :: Web Environment
Classifier: Framework :: Django
Classifier: Framework :: Django :: 4.2
Classifier: Intended Audience :: Developers
Classifier: License :: OSI Approved :: MIT License
Classifier: Operating System :: OS Independent
Classifier: Programming Language :: Python
Classifier: Programming Language :: Python :: 3
Classifier: Programming Language :: Python :: 3.8
Classifier: Programming Language :: Python :: 3.9
Classifier: Programming Language :: Python :: 3.10
Classifier: Programming Language :: Python :: 3.11
Classifier: Programming Language :: Python :: 3.12
Classifier: Topic :: Software Development
Classifier: Topic :: Software Development :: Libraries :: Python Modules
Requires-Python: >=3.8
License-File: AUTHORS
Requires-Dist: cryptography>=41.0.7
Requires-Dist: django-pipeline~=3.1.0
Requires-Dist: Django~=4.2.17
Requires-Dist: dnspython>=2.3.0
Requires-Dist: housekeeping~=1.1
Requires-Dist: importlib-metadata>=6.6
Requires-Dist: importlib-resources>=5.9
Requires-Dist: packaging>=23.1
Requires-Dist: Pillow>=6.2
Requires-Dist: publicsuffixlist~=0.10.0
Requires-Dist: python-dateutil>=2.7
Requires-Dist: pytz
Requires-Dist: typing_extensions>=4.12.2
Dynamic: license-file
